Workbook

Sheet Roles & Access
A4: Role | B4: Main Responsibility | C4: Data Access
A5: Management / Head Office | B5: Overall business monitoring and decision-making | C5: All 4 Plants + 10 Warehouses
A6: Plant Manager | B6: Monitor production and plant performance | C6: Own Manufacturing Plant
A7: Warehouse Manager | B7: Monitor inventory, stock movement and warehouse operations | C7: Own Warehouse
A8: Supply Chain Manager | B8: Monitor stock, transfers, distribution and supply | C8: All Plants + Warehouses
A9: Production Manager | B9: Monitor production quantity, efficiency and wastage | C9: Manufacturing Plant
A10: Quality Manager | B10: Monitor product quality and rejection | C10: Plant / Product
A11: Sales & Distribution Manager | B11: Monitor dispatch, sales and distribution | C11: Warehouses / Distribution
A12: Inventory Manager | B12: Monitor stock availability and ageing | C12: Warehouses + Plants

Sheet Role KPIs
A4: Role | B4: Data Access | C4: KPI | D4: Review
A5: Management / Head Office | B5: =INDEX('Roles & Access'!$C$5:$C$12,MATCH(A5,'Roles & Access'!$A$5:$A$12,0)) -> All 4 Plants + 10 Warehouses | C5: Production vs plan (all plants) | D5: Daily / Monthly
A6: Management / Head Office | B6: =INDEX('Roles & Access'!$C$5:$C$12,MATCH(A6,'Roles & Access'!$A$5:$A$12,0)) -> All 4 Plants + 10 Warehouses | C6: Sales vs target | D6: Monthly
A7: Management / Head Office | B7: =INDEX('Roles & Access'!$C$5:$C$12,MATCH(A7,'Roles & Access'!$A$5:$A$12,0)) -> All 4 Plants + 10 Warehouses | C7: Order fill rate (network) | D7: Weekly
A8: Management / Head Office | B8: =INDEX('Roles & Access'!$C$5:$C$12,MATCH(A8,'Roles & Access'!$A$5:$A$12,0)) -> All 4 Plants + 10 Warehouses | C8: Overall quality rejection | D8: Weekly
A9: Management / Head Office | B9: =INDEX('Roles & Access'!$C$5:$C$12,MATCH(A9,'Roles & Access'!$A$5:$A$12,0)) -> All 4 Plants + 10 Warehouses | C9: Inventory days (network) | D9: Monthly
A10: Management / Head Office | B10: =INDEX('Roles & Access'!$C$5:$C$12,MATCH(A10,'Roles & Access'!$A$5:$A$12,0)) -> All 4 Plants + 10 Warehouses | C10: Plant-wise OEE comparison | D10: Monthly
A11: Plant Manager | B11: =INDEX('Roles & Access'!$C$5:$C$12,MATCH(A11,'Roles & Access'!$A$5:$A$12,0)) -> Own Manufacturing Plant | C11: Production vs plan | D11: Daily
A12: Plant Manager | B12: =INDEX('Roles & Access'!$C$5:$C$12,MATCH(A12,'Roles & Access'!$A$5:$A$12,0)) -> Own Manufacturing Plant | C12: Overall Equipment Effectiveness (OEE) | D12: Weekly
A13: Plant Manager | B13: =INDEX('Roles & Access'!$C$5:$C$12,MATCH(A13,'Roles & Access'!$A$5:$A$12,0)) -> Own Manufacturing Plant | C13: Unplanned downtime | D13: Weekly
A14: Plant Manager | B14: =INDEX('Roles & Access'!$C$5:$C$12,MATCH(A14,'Roles & Access'!$A$5:$A$12,0)) -> Own Manufacturing Plant | C14: Rejection rate | D14: Daily
A15: Plant Manager | B15: =INDEX('Roles & Access'!$C$5:$C$12,MATCH(A15,'Roles & Access'!$A$5:$A$12,0)) -> Own Manufacturing Plant | C15: Wastage / process loss | D15: Weekly
A16: Plant Manager | B16: =INDEX('Roles & Access'!$C$5:$C$12,MATCH(A16,'Roles & Access'!$A$5:$A$12,0)) -> Own Manufacturing Plant | C16: Safety incidents | D16: Monthly
... A52: Inventory Manager | B52: =INDEX('Roles & Access'!$C$5:$C$12,MATCH(A52,'Roles & Access'!$A$5:$A$12,0)) -> Warehouses + Plants | C52: Inventory days | D52: Monthly
